{"objects":{"components":[{"uuid":"e9820c15-ff25-4d06-8b64-6f1d6f29c92d-0030a4d1","name":"连接的实心几何图形","familyName":"","typeName":"连接的实心几何图形","typeId":-1,"revitId":"3187921","typec":"","type":"GeomCombination","properties":{"Name":"连接的实心几何图形","ElementPoint":null,"ElementRotation":null,"Mirrored":null,"HandFlipped":null,"HandOrientation":null,"FacingFlipped":null,"FacingOrientation":null,"Translation":null,"matrix":null,"BoundingBox":"(0.787401575, 0.147637795, 1.640419948),(0.000000000, 0.000000000, 0.000000000)","子类别":"<无>","材质":"<按类别>","可见":"是"}},{"uuid":"e9820c15-ff25-4d06-8b64-6f1d6f29c92d-0030a4dd","name":"拉伸","familyName":"","typeName":"拉伸","typeId":-1,"revitId":"3187933","typec":"","type":"Extrusion","properties":{"Name":"拉伸","ElementPoint":null,"ElementRotation":null,"Mirrored":null,"HandFlipped":null,"HandOrientation":null,"FacingFlipped":null,"FacingOrientation":null,"Translation":null,"matrix":null,"BoundingBox":"(0.748031496, 0.141076115, 1.171259843),(0.314960630, -0.200131234, 0.738188976)","拉伸终点":"61","拉伸起点":"-43","可见":"是","工作平面":"参照平面 : 中心(前/后)","子类别":"<无>","材质":"<按类别>","实心/空心":"实心"}},{"uuid":"e9820c15-ff25-4d06-8b64-6f1d6f29c92d-0030a4e1","name":"拉伸","familyName":"","typeName":"拉伸","typeId":-1,"revitId":"3187937","typec":"","type":"Extrusion","properties":{"Name":"拉伸","ElementPoint":null,"ElementRotation":null,"Mirrored":null,"HandFlipped":null,"HandOrientation":null,"FacingFlipped":null,"FacingOrientation":null,"Translation":null,"matrix":null,"BoundingBox":"(0.672572178, -0.200131234, 1.067913386),(0.390419948, -0.331364829, 0.841535433)","拉伸终点":"101","拉伸起点":"61","可见":"是","工作平面":"参照平面 : 中心(前/后)","子类别":"<无>","材质":"<按类别>","实心/空心":"实心"}},{"uuid":"e9820c15-ff25-4d06-8b64-6f1d6f29c92d-0030a4e9","name":"拉伸","familyName":"","typeName":"拉伸","typeId":-1,"revitId":"3187945","typec":"","type":"Extrusion","properties":{"Name":"拉伸","ElementPoint":null,"ElementRotation":null,"Mirrored":null,"HandFlipped":null,"HandOrientation":null,"FacingFlipped":null,"FacingOrientation":null,"Translation":null,"matrix":null,"BoundingBox":"(0.574146982, 0.298556430, 0.997375328),(0.488845144, 0.147637795, 0.912073491)","拉伸终点":"-91","拉伸起点":"-45","可见":"是","工作平面":"参照平面 : 中心(前/后)","子类别":"<无>","材质":"<按类别>","实心/空心":"实心"}},{"uuid":"e9820c15-ff25-4d06-8b64-6f1d6f29c92d-0030a4ee","name":"拉伸","familyName":"","typeName":"拉伸","typeId":-1,"revitId":"3187950","typec":"","type":"Extrusion","properties":{"Name":"拉伸","ElementPoint":null,"ElementRotation":null,"Mirrored":null,"HandFlipped":null,"HandOrientation":null,"FacingFlipped":null,"FacingOrientation":null,"Translation":null,"matrix":null,"BoundingBox":"(0.187007874, 0.246062992, 0.583704615),(0.000000000, 0.147637795, 0.354615595)","拉伸终点":"-75","拉伸起点":"-45","可见":"是","工作平面":"参照平面 : 中心(前/后)","子类别":"<无>","材质":"<按类别>","实心/空心":"实心"}},{"uuid":"e9820c15-ff25-4d06-8b64-6f1d6f29c92d-0030a50a","name":"连接的实心几何图形","familyName":"","typeName":"连接的实心几何图形","typeId":-1,"revitId":"3187978","typec":"","type":"GeomCombination","properties":{"Name":"连接的实心几何图形","ElementPoint":null,"ElementRotation":null,"Mirrored":null,"HandFlipped":null,"HandOrientation":null,"FacingFlipped":null,"FacingOrientation":null,"Translation":null,"matrix":null,"BoundingBox":"(0.223097113, 0.449475066, 0.541338583),(0.000000000, 0.147637795, 0.180446194)","子类别":"<无>","材质":"<按类别>","可见":"是"}},{"uuid":"e9820c15-ff25-4d06-8b64-6f1d6f29c92d-0030a525","name":"连接的实心几何图形","familyName":"","typeName":"连接的实心几何图形","typeId":-1,"revitId":"3188005","typec":"","type":"GeomCombination","properties":{"Name":"连接的实心几何图形","ElementPoint":null,"ElementRotation":null,"Mirrored":null,"HandFlipped":null,"HandOrientation":null,"FacingFlipped":null,"FacingOrientation":null,"Translation":null,"matrix":null,"BoundingBox":"(0.180446194, 0.426509186, 1.991469816),(0.000000000, 0.262467192, 0.392060367)","子类别":"<无>","材质":"<按类别>","可见":"是"}},{"uuid":"e9820c15-ff25-4d06-8b64-6f1d6f29c92d-0030a578","name":"连接的实心几何图形","familyName":"","typeName":"连接的实心几何图形","typeId":-1,"revitId":"3188088","typec":"","type":"GeomCombination","properties":{"Name":"连接的实心几何图形","ElementPoint":null,"ElementRotation":null,"Mirrored":null,"HandFlipped":null,"HandOrientation":null,"FacingFlipped":null,"FacingOrientation":null,"Translation":null,"matrix":null,"BoundingBox":"(0.328083990, 0.449475066, 0.469160105),(0.223097113, 0.157480315, 0.305118110)","子类别":"<无>","材质":"<按类别>","可见":"是"}},{"uuid":"e9820c15-ff25-4d06-8b64-6f1d6f29c92d-0030a583","name":"连接的实心几何图形","familyName":"","typeName":"连接的实心几何图形","typeId":-1,"revitId":"3188099","typec":"","type":"GeomCombination","properties":{"Name":"连接的实心几何图形","ElementPoint":null,"ElementRotation":null,"Mirrored":null,"HandFlipped":null,"HandOrientation":null,"FacingFlipped":null,"FacingOrientation":null,"Translation":null,"matrix":null,"BoundingBox":"(0.000000000, 0.426509186, 2.180055430),(-0.887961831, 0.262467192, 0.718808797)","子类别":"<无>","材质":"门","可见":"是"}}]}}