{"objects":{"components":[{"uuid":"95c81fd0-9e8a-4f2c-b028-a68bb5ba1047-001c64d4","name":"水管-内外热镀锌钢管","familyName":"管道类型","typeName":"水管-内外热镀锌钢管","typeId":1121512,"revitId":"1860820","type":"Pipe","category":"OST_PipeCurves","properties":{"Category":"管道","Name":"水管-内外热镀锌钢管","系统分类":"家用冷水","系统类型":"给水管","系统名称":"J 4","系统缩写":"J","管段":"内外热镀锌钢管 - GB/T3091","直径":"80 mm","连接类型":"常规","粗糙度":"0.00200 mm","材质":"内外热镀锌钢管","规格/类型":"GB/T3091","管内底标高":"-160","剖面":"21","面积":"1","其他流量":"0.0 L/s","流量":"0.0 L/s","雷诺数":"0","相对粗糙度":"0.000025","流量状态":"层流","摩擦系数":"0","速度":"0.0 m/s","摩擦":"0.00 Pa/m","压降":"0.0 Pa","图像":"<无>","总体大小":"80 mm","隔热层厚度":"0 mm","卫浴装置当量":"0","外径":"89 mm","内径":"81 mm","尺寸":"80 mm","给排水工作压力":"0.0 Pa","管道材质":"<按类别>","气管管径":"0 mm","液管管径":"0 mm","创建的阶段":"新构造","拆除的阶段":"无","设计选项":"主模型","水平对正":"中心","垂直对正":"中","参照标高":"站厅层装修完成面","偏移":"2300","开始偏移":"2300","端点偏移":"2300","长度":"2082","坡度":"0.00%","类型图像":"<无>","成本":"0.00"}},{"uuid":"95c81fd0-9e8a-4f2c-b028-a68bb5ba1047-001c64d5","name":"","familyName":"管道类型","typeName":"","typeId":-1,"revitId":"1860821","type":"Element","category":"OST_PipeCurvesCenterLine","properties":{"Category":"中心线","Name":"","系统分类":"家用冷水","系统类型":"给水管","系统名称":"J 4","系统缩写":"J","管段":"内外热镀锌钢管 - GB/T3091","直径":"80 mm","连接类型":"常规","粗糙度":"0.00200 mm","材质":"内外热镀锌钢管","规格/类型":"GB/T3091","管内底标高":"-160","剖面":"0","面积":"1","其他流量":"0.0 L/s","流量":"0.0 L/s","雷诺数":"0","相对粗糙度":"0","流量状态":"层流","摩擦系数":"0","速度":"0.0 m/s","摩擦":"0.00 Pa/m","压降":"0.0 Pa","图像":"<无>","总体大小":"80 mm","隔热层厚度":"0 mm","卫浴装置当量":"0","外径":"89 mm","内径":"81 mm","尺寸":"80 mm","给排水工作压力":"0.0 Pa","管道材质":"<按类别>","气管管径":"0 mm","液管管径":"0 mm","创建的阶段":"新构造","拆除的阶段":"无","设计选项":"主模型","水平对正":"中心","垂直对正":"中","参照标高":"站厅层装修完成面","偏移":"2300","开始偏移":"2300","端点偏移":"2300","长度":"2082","坡度":"0.00%"}},{"uuid":"95c81fd0-9e8a-4f2c-b028-a68bb5ba1047-001c64de","name":"弯头-丝扣","familyName":"管道-弯头-丝扣","typeName":"弯头-丝扣","typeId":1088740,"revitId":"1860830","type":"FamilyInstance","category":"OST_PipeFitting","properties":{"Category":"管件","Name":"弯头-丝扣","总体大小":"80 mm-80 mm","隔热层厚度":"0 mm","重要路径":"否","压降":"0.0 Pa","标高":"站厅层装修完成面","主体":"标高 : 站厅层装修完成面","偏移":"2300","创建的阶段":"新构造","拆除的阶段":"无","给排水工作压力":"0.0 Pa","系统分类":"家用冷水","系统类型":"给水管","系统名称":"J 4","系统缩写":"J","损失方法":"3bf616f9-6b98-4a21-80ff-da1120c8f6d6","管件材质":"钢塑复合","使用注释比例":"是","公称半径":"40 mm","公称直径":"80 mm","角度":"90.00°","尺寸":"80 mm-80 mm","图像":"<无>","设计选项":"主模型","IsCustom":"否","中心到端点":"78 mm","扎带外径":"97 mm","扎带宽度":"9 mm","管件外径":"89 mm","螺纹长度":"28 mm","金属厚度":"4 mm","长度 2":"78 mm","长度 1":"78 mm","管件外半径":"44 mm","找不到中心到端点":"80 mm","中心到端点标签":"78 mm","中心半径":"50 mm","扎带外半径":"48 mm","角度 1":"90.00°","K 系数":"0","构件分类编码":"20.80.05.20.04.05","类型图像":"<无>","成本":"0.00","查找表名称":"弯头 - 钢塑复合管 - 丝扣"}},{"uuid":"95c81fd0-9e8a-4f2c-b028-a68bb5ba1047-001c64df","name":"","familyName":"管道-弯头-丝扣","typeName":"","typeId":-1,"revitId":"1860831","type":"Element","category":"OST_PipeFittingCenterLine","properties":{"Category":"中心线","Name":"","金属厚度":"4 mm","给排水工作压力":"0.0 Pa","管件材质":"钢塑复合","长度 2":"78 mm","长度 1":"78 mm","管件外半径":"44 mm","管件外径":"89 mm","公称半径":"40 mm","公称直径":"80 mm","找不到中心到端点":"80 mm","中心到端点":"78 mm","中心到端点标签":"78 mm","中心半径":"50 mm","螺纹长度":"28 mm","扎带外半径":"48 mm","扎带宽度":"9 mm","扎带外径":"97 mm","角度 1":"90.00°","角度":"90.00°","标高":"站厅层装修完成面","主体":"标高 : 站厅层装修完成面","偏移":"2300","系统分类":"家用冷水","系统类型":"给水管","系统名称":"J 4","系统缩写":"J","损失方法":"3bf616f9-6b98-4a21-80ff-da1120c8f6d6","重要路径":"否","图像":"<无>","总体大小":"80 mm-80 mm","隔热层厚度":"0 mm","压降":"0.0 Pa","使用注释比例":"是","尺寸":"80 mm-80 mm","IsCustom":"否","创建的阶段":"新构造","拆除的阶段":"无","设计选项":"主模型"}},{"uuid":"95c81fd0-9e8a-4f2c-b028-a68bb5ba1047-001c6508","name":"水管-内外热镀锌钢管","familyName":"管道类型","typeName":"水管-内外热镀锌钢管","typeId":1121512,"revitId":"1860872","type":"Pipe","category":"OST_PipeCurves","properties":{"Category":"管道","Name":"水管-内外热镀锌钢管","系统分类":"湿式消防系统","系统类型":"消防水管","系统名称":"XH 2","系统缩写":"XH","管段":"内外热镀锌钢管 - GB/T3091","直径":"150 mm","连接类型":"常规","粗糙度":"0.00200 mm","材质":"内外热镀锌钢管","规格/类型":"GB/T3091","管内底标高":"2300","剖面":"13","面积":"1","相对粗糙度":"0.000013","图像":"<无>","总体大小":"150 mm","隔热层厚度":"0 mm","外径":"168 mm","内径":"159 mm","尺寸":"150 mm","给排水工作压力":"0.0 Pa","管道材质":"<按类别>","气管管径":"0 mm","液管管径":"0 mm","创建的阶段":"新构造","拆除的阶段":"无","设计选项":"主模型","水平对正":"中心","垂直对正":"中","参照标高":"站厅层装修完成面","偏移":"4800","开始偏移":"4800","端点偏移":"4800","长度":"1408","坡度":"0.00%","类型图像":"<无>","成本":"0.00"}},{"uuid":"95c81fd0-9e8a-4f2c-b028-a68bb5ba1047-001c6509","name":"","familyName":"管道类型","typeName":"","typeId":-1,"revitId":"1860873","type":"Element","category":"OST_PipeCurvesCenterLine","properties":{"Category":"中心线","Name":"","系统分类":"湿式消防系统","系统类型":"消防水管","系统名称":"XH 2","系统缩写":"XH","管段":"内外热镀锌钢管 - GB/T3091","直径":"150 mm","连接类型":"常规","粗糙度":"0.00200 mm","材质":"内外热镀锌钢管","规格/类型":"GB/T3091","管内底标高":"2300","剖面":"0","面积":"1","相对粗糙度":"0","图像":"<无>","总体大小":"150 mm","隔热层厚度":"0 mm","外径":"168 mm","内径":"159 mm","尺寸":"150 mm","给排水工作压力":"0.0 Pa","管道材质":"<按类别>","气管管径":"0 mm","液管管径":"0 mm","创建的阶段":"新构造","拆除的阶段":"无","设计选项":"主模型","水平对正":"中心","垂直对正":"中","参照标高":"站厅层装修完成面","偏移":"4800","开始偏移":"4800","端点偏移":"4800","长度":"1408","坡度":"0.00%"}},{"uuid":"95c81fd0-9e8a-4f2c-b028-a68bb5ba1047-001c6512","name":"弯头-卡箍","familyName":"管道-弯头-卡箍","typeName":"弯头-卡箍","typeId":1273842,"revitId":"1860882","type":"FamilyInstance","category":"OST_PipeFitting","properties":{"Category":"管件","Name":"弯头-卡箍","总体大小":"150 mm-150 mm","隔热层厚度":"0 mm","重要路径":"否","压降":"0.0 Pa","标高":"站厅层装修完成面","主体":"标高 : 站厅层装修完成面","偏移":"4800","创建的阶段":"新构造","拆除的阶段":"无","系统分类":"湿式消防系统","系统类型":"消防水管","系统名称":"XH 2","系统缩写":"XH","损失方法":"3bf616f9-6b98-4a21-80ff-da1120c8f6d6","使用注释比例":"是","公称半径":"75 mm","公称直径":"150 mm","管件外径":"168 mm","中心到端点":"152 mm","角度":"90.00°","尺寸":"150 mm-150 mm","图像":"<无>","设计选项":"主模型","管件外半径":"84 mm","中心到端点标签":"152 mm","中心半径":"152 mm","IsCustom":"否","K 系数表":"Regular 45, 90 and 180 Elbow","K 系数":"0","材质":"消防红","类型图像":"<无>","成本":"0.00","查找表名称":"Elbow - Generic"}},{"uuid":"95c81fd0-9e8a-4f2c-b028-a68bb5ba1047-001c6513","name":"","familyName":"管道-弯头-卡箍","typeName":"","typeId":-1,"revitId":"1860883","type":"Element","category":"OST_PipeFittingCenterLine","properties":{"Category":"中心线","Name":"","公称半径":"75 mm","公称直径":"150 mm","管件外半径":"84 mm","管件外径":"168 mm","中心到端点标签":"152 mm","中心到端点":"152 mm","中心半径":"152 mm","角度":"90.00°","标高":"站厅层装修完成面","主体":"标高 : 站厅层装修完成面","偏移":"4800","系统分类":"湿式消防系统","系统类型":"消防水管","系统名称":"XH 2","系统缩写":"XH","损失方法":"3bf616f9-6b98-4a21-80ff-da1120c8f6d6","重要路径":"否","图像":"<无>","总体大小":"150 mm-150 mm","隔热层厚度":"0 mm","压降":"0.0 Pa","使用注释比例":"是","尺寸":"150 mm-150 mm","IsCustom":"否","创建的阶段":"新构造","拆除的阶段":"无","设计选项":"主模型"}},{"uuid":"0a0035d8-93df-4331-9bc8-d4215dd0740c-001c655d","name":"水管-内外热镀锌钢管","familyName":"管道类型","typeName":"水管-内外热镀锌钢管","typeId":1121512,"revitId":"1860957","type":"Pipe","category":"OST_PipeCurves","properties":{"Category":"管道","Name":"水管-内外热镀锌钢管","系统分类":"其他","系统类型":"压力废水管","系统名称":"YF 2","系统缩写":"YF","管段":"内外热镀锌钢管 - GB/T3091","直径":"80 mm","连接类型":"常规","粗糙度":"0.00200 mm","材质":"内外热镀锌钢管","规格/类型":"GB/T3091","管内底标高":"1040","剖面":"1","面积":"0","相对粗糙度":"0.000025","图像":"<无>","总体大小":"80 mm","隔热层厚度":"0 mm","外径":"89 mm","内径":"81 mm","尺寸":"80 mm","给排水工作压力":"0.0 Pa","管道材质":"<按类别>","气管管径":"0 mm","液管管径":"0 mm","创建的阶段":"新构造","拆除的阶段":"无","设计选项":"主模型","水平对正":"中心","垂直对正":"中","参照标高":"站厅层装修完成面","偏移":"3500","开始偏移":"3500","端点偏移":"3500","长度":"1502","坡度":"0.00%","类型图像":"<无>","成本":"0.00"}},{"uuid":"0a0035d8-93df-4331-9bc8-d4215dd0740c-001c655e","name":"","familyName":"管道类型","typeName":"","typeId":-1,"revitId":"1860958","type":"Element","category":"OST_PipeCurvesCenterLine","properties":{"Category":"中心线","Name":"","系统分类":"其他","系统类型":"压力废水管","系统名称":"YF 2","系统缩写":"YF","管段":"内外热镀锌钢管 - GB/T3091","直径":"80 mm","连接类型":"常规","粗糙度":"0.00200 mm","材质":"内外热镀锌钢管","规格/类型":"GB/T3091","管内底标高":"1040","剖面":"0","面积":"0","相对粗糙度":"0","图像":"<无>","总体大小":"80 mm","隔热层厚度":"0 mm","外径":"89 mm","内径":"81 mm","尺寸":"80 mm","给排水工作压力":"0.0 Pa","管道材质":"<按类别>","气管管径":"0 mm","液管管径":"0 mm","创建的阶段":"新构造","拆除的阶段":"无","设计选项":"主模型","水平对正":"中心","垂直对正":"中","参照标高":"站厅层装修完成面","偏移":"3500","开始偏移":"3500","端点偏移":"3500","长度":"1502","坡度":"0.00%"}},{"uuid":"0a0035d8-93df-4331-9bc8-d4215dd0740c-001c655f","name":"YF 2","familyName":"管道系统","typeName":"YF 2","typeId":976772,"revitId":"1860959","type":"PipingSystem","category":"OST_PipingSystem","properties":{"Category":"管道系统","Name":"YF 2","图像":"<无>","图元数":"0","系统名称":"YF 2","体积":"20.1 L","设计选项":"主模型","类型图像":"<无>","双线下降符号":"阴阳","双线上升符号":"轮廓","单线下降符号":"弯曲 - ¾ 圆","单线上升符号":"轮廓","单线 T 形三通向上符号":"轮廓","单线 T 形三通向下符号":"T 形三通 - 半圆","计算":"无","缩写":"YF","系统分类":"其他","材质":"MEP_压力废水管系统颜色"}},{"uuid":"0a0035d8-93df-4331-9bc8-d4215dd0740c-001c6566","name":"水管-内外热镀锌钢管","familyName":"管道类型","typeName":"水管-内外热镀锌钢管","typeId":1121512,"revitId":"1860966","type":"Pipe","category":"OST_PipeCurves","properties":{"Category":"管道","Name":"水管-内外热镀锌钢管","系统分类":"其他","系统类型":"压力废水管","系统名称":"YF 2","系统缩写":"YF","管段":"内外热镀锌钢管 - GB/T3091","直径":"80 mm","连接类型":"常规","粗糙度":"0.00200 mm","材质":"内外热镀锌钢管","规格/类型":"GB/T3091","管内底标高":"1040","剖面":"1","面积":"1","相对粗糙度":"0.000025","图像":"<无>","总体大小":"80 mm","隔热层厚度":"0 mm","外径":"89 mm","内径":"81 mm","尺寸":"80 mm","给排水工作压力":"0.0 Pa","管道材质":"<按类别>","气管管径":"0 mm","液管管径":"0 mm","创建的阶段":"新构造","拆除的阶段":"无","设计选项":"主模型","水平对正":"中心","垂直对正":"中","参照标高":"站厅层装修完成面","偏移":"3500","开始偏移":"3500","端点偏移":"3500","长度":"2246","坡度":"0.00%","类型图像":"<无>","成本":"0.00"}},{"uuid":"0a0035d8-93df-4331-9bc8-d4215dd0740c-001c6567","name":"","familyName":"管道类型","typeName":"","typeId":-1,"revitId":"1860967","type":"Element","category":"OST_PipeCurvesCenterLine","properties":{"Category":"中心线","Name":"","系统分类":"其他","系统类型":"压力废水管","系统名称":"YF 2","系统缩写":"YF","管段":"内外热镀锌钢管 - GB/T3091","直径":"80 mm","连接类型":"常规","粗糙度":"0.00200 mm","材质":"内外热镀锌钢管","规格/类型":"GB/T3091","管内底标高":"1040","剖面":"0","面积":"1","相对粗糙度":"0","图像":"<无>","总体大小":"80 mm","隔热层厚度":"0 mm","外径":"89 mm","内径":"81 mm","尺寸":"80 mm","给排水工作压力":"0.0 Pa","管道材质":"<按类别>","气管管径":"0 mm","液管管径":"0 mm","创建的阶段":"新构造","拆除的阶段":"无","设计选项":"主模型","水平对正":"中心","垂直对正":"中","参照标高":"站厅层装修完成面","偏移":"3500","开始偏移":"3500","端点偏移":"3500","长度":"2246","坡度":"0.00%"}},{"uuid":"0a0035d8-93df-4331-9bc8-d4215dd0740c-001c656e","name":"弯头-丝扣","familyName":"管道-弯头-丝扣","typeName":"弯头-丝扣","typeId":1088740,"revitId":"1860974","type":"FamilyInstance","category":"OST_PipeFitting","properties":{"Category":"管件","Name":"弯头-丝扣","总体大小":"80 mm-80 mm","隔热层厚度":"0 mm","重要路径":"否","压降":"0.0 Pa","标高":"站厅层装修完成面","主体":"标高 : 站厅层装修完成面","偏移":"3500","创建的阶段":"新构造","拆除的阶段":"无","给排水工作压力":"0.0 Pa","系统分类":"其他","系统类型":"压力废水管","系统名称":"YF 2","系统缩写":"YF","损失方法":"3bf616f9-6b98-4a21-80ff-da1120c8f6d6","管件材质":"钢塑复合","使用注释比例":"是","公称半径":"40 mm","公称直径":"80 mm","角度":"90.00°","尺寸":"80 mm-80 mm","图像":"<无>","设计选项":"主模型","IsCustom":"否","中心到端点":"78 mm","扎带外径":"97 mm","扎带宽度":"9 mm","管件外径":"89 mm","螺纹长度":"28 mm","金属厚度":"4 mm","长度 2":"78 mm","长度 1":"78 mm","管件外半径":"44 mm","找不到中心到端点":"80 mm","中心到端点标签":"78 mm","中心半径":"50 mm","扎带外半径":"48 mm","角度 1":"90.00°","K 系数":"0","构件分类编码":"20.80.05.20.04.05","类型图像":"<无>","成本":"0.00","查找表名称":"弯头 - 钢塑复合管 - 丝扣"}},{"uuid":"0a0035d8-93df-4331-9bc8-d4215dd0740c-001c656f","name":"","familyName":"管道-弯头-丝扣","typeName":"","typeId":-1,"revitId":"1860975","type":"Element","category":"OST_PipeFittingCenterLine","properties":{"Category":"中心线","Name":"","金属厚度":"4 mm","给排水工作压力":"0.0 Pa","管件材质":"钢塑复合","长度 2":"78 mm","长度 1":"78 mm","管件外半径":"44 mm","管件外径":"89 mm","公称半径":"40 mm","公称直径":"80 mm","找不到中心到端点":"80 mm","中心到端点":"78 mm","中心到端点标签":"78 mm","中心半径":"50 mm","螺纹长度":"28 mm","扎带外半径":"48 mm","扎带宽度":"9 mm","扎带外径":"97 mm","角度 1":"90.00°","角度":"90.00°","标高":"站厅层装修完成面","主体":"标高 : 站厅层装修完成面","偏移":"3500","系统分类":"其他","系统类型":"压力废水管","系统名称":"YF 2","系统缩写":"YF","损失方法":"3bf616f9-6b98-4a21-80ff-da1120c8f6d6","重要路径":"否","图像":"<无>","总体大小":"80 mm-80 mm","隔热层厚度":"0 mm","压降":"0.0 Pa","使用注释比例":"是","尺寸":"80 mm-80 mm","IsCustom":"否","创建的阶段":"新构造","拆除的阶段":"无","设计选项":"主模型"}},{"uuid":"0a0035d8-93df-4331-9bc8-d4215dd0740c-001c6578","name":"水管-内外热镀锌钢管","familyName":"管道类型","typeName":"水管-内外热镀锌钢管","typeId":1121512,"revitId":"1860984","type":"Pipe","category":"OST_PipeCurves","properties":{"Category":"管道","Name":"水管-内外热镀锌钢管","系统分类":"其他","系统类型":"压力废水管","系统名称":"YF 3","系统缩写":"YF","管段":"内外热镀锌钢管 - GB/T3091","直径":"80 mm","连接类型":"常规","粗糙度":"0.00200 mm","材质":"内外热镀锌钢管","规格/类型":"GB/T3091","管内底标高":"1040","剖面":"1","面积":"1","相对粗糙度":"0.000025","图像":"<无>","总体大小":"80 mm","隔热层厚度":"0 mm","外径":"89 mm","内径":"81 mm","尺寸":"80 mm","给排水工作压力":"0.0 Pa","管道材质":"<按类别>","气管管径":"0 mm","液管管径":"0 mm","创建的阶段":"新构造","拆除的阶段":"无","设计选项":"主模型","水平对正":"中心","垂直对正":"中","参照标高":"站厅层装修完成面","偏移":"3500","开始偏移":"3500","端点偏移":"3500","长度":"2322","坡度":"0.00%","类型图像":"<无>","成本":"0.00"}},{"uuid":"0a0035d8-93df-4331-9bc8-d4215dd0740c-001c6579","name":"","familyName":"管道类型","typeName":"","typeId":-1,"revitId":"1860985","type":"Element","category":"OST_PipeCurvesCenterLine","properties":{"Category":"中心线","Name":"","系统分类":"其他","系统类型":"压力废水管","系统名称":"YF 3","系统缩写":"YF","管段":"内外热镀锌钢管 - GB/T3091","直径":"80 mm","连接类型":"常规","粗糙度":"0.00200 mm","材质":"内外热镀锌钢管","规格/类型":"GB/T3091","管内底标高":"1040","剖面":"0","面积":"1","相对粗糙度":"0","图像":"<无>","总体大小":"80 mm","隔热层厚度":"0 mm","外径":"89 mm","内径":"81 mm","尺寸":"80 mm","给排水工作压力":"0.0 Pa","管道材质":"<按类别>","气管管径":"0 mm","液管管径":"0 mm","创建的阶段":"新构造","拆除的阶段":"无","设计选项":"主模型","水平对正":"中心","垂直对正":"中","参照标高":"站厅层装修完成面","偏移":"3500","开始偏移":"3500","端点偏移":"3500","长度":"2322","坡度":"0.00%"}},{"uuid":"0a0035d8-93df-4331-9bc8-d4215dd0740c-001c657a","name":"YF 3","familyName":"管道系统","typeName":"YF 3","typeId":976772,"revitId":"1860986","type":"PipingSystem","category":"OST_PipingSystem","properties":{"Category":"管道系统","Name":"YF 3","图像":"<无>","图元数":"0","系统名称":"YF 3","体积":"20.1 L","设计选项":"主模型","类型图像":"<无>","双线下降符号":"阴阳","双线上升符号":"轮廓","单线下降符号":"弯曲 - ¾ 圆","单线上升符号":"轮廓","单线 T 形三通向上符号":"轮廓","单线 T 形三通向下符号":"T 形三通 - 半圆","计算":"无","缩写":"YF","系统分类":"其他","材质":"MEP_压力废水管系统颜色"}},{"uuid":"0a0035d8-93df-4331-9bc8-d4215dd0740c-001c6580","name":"水管-内外热镀锌钢管","familyName":"管道类型","typeName":"水管-内外热镀锌钢管","typeId":1121512,"revitId":"1860992","type":"Pipe","category":"OST_PipeCurves","properties":{"Category":"管道","Name":"水管-内外热镀锌钢管","系统分类":"其他","系统类型":"压力废水管","系统名称":"YF 3","系统缩写":"YF","管段":"内外热镀锌钢管 - GB/T3091","直径":"80 mm","连接类型":"常规","粗糙度":"0.00200 mm","材质":"内外热镀锌钢管","规格/类型":"GB/T3091","管内底标高":"1040","剖面":"1","面积":"0","相对粗糙度":"0.000025","图像":"<无>","总体大小":"80 mm","隔热层厚度":"0 mm","外径":"89 mm","内径":"81 mm","尺寸":"80 mm","给排水工作压力":"0.0 Pa","管道材质":"<按类别>","气管管径":"0 mm","液管管径":"0 mm","创建的阶段":"新构造","拆除的阶段":"无","设计选项":"主模型","水平对正":"中心","垂直对正":"中","参照标高":"站厅层装修完成面","偏移":"3500","开始偏移":"3500","端点偏移":"3500","长度":"1442","坡度":"0.00%","类型图像":"<无>","成本":"0.00"}},{"uuid":"0a0035d8-93df-4331-9bc8-d4215dd0740c-001c6581","name":"","familyName":"管道类型","typeName":"","typeId":-1,"revitId":"1860993","type":"Element","category":"OST_PipeCurvesCenterLine","properties":{"Category":"中心线","Name":"","系统分类":"其他","系统类型":"压力废水管","系统名称":"YF 3","系统缩写":"YF","管段":"内外热镀锌钢管 - GB/T3091","直径":"80 mm","连接类型":"常规","粗糙度":"0.00200 mm","材质":"内外热镀锌钢管","规格/类型":"GB/T3091","管内底标高":"1040","剖面":"0","面积":"0","相对粗糙度":"0","图像":"<无>","总体大小":"80 mm","隔热层厚度":"0 mm","外径":"89 mm","内径":"81 mm","尺寸":"80 mm","给排水工作压力":"0.0 Pa","管道材质":"<按类别>","气管管径":"0 mm","液管管径":"0 mm","创建的阶段":"新构造","拆除的阶段":"无","设计选项":"主模型","水平对正":"中心","垂直对正":"中","参照标高":"站厅层装修完成面","偏移":"3500","开始偏移":"3500","端点偏移":"3500","长度":"1442","坡度":"0.00%"}},{"uuid":"0a0035d8-93df-4331-9bc8-d4215dd0740c-001c6586","name":"弯头-丝扣","familyName":"管道-弯头-丝扣","typeName":"弯头-丝扣","typeId":1088740,"revitId":"1860998","type":"FamilyInstance","category":"OST_PipeFitting","properties":{"Category":"管件","Name":"弯头-丝扣","总体大小":"80 mm-80 mm","隔热层厚度":"0 mm","重要路径":"否","压降":"0.0 Pa","标高":"站厅层装修完成面","主体":"标高 : 站厅层装修完成面","偏移":"3500","创建的阶段":"新构造","拆除的阶段":"无","给排水工作压力":"0.0 Pa","系统分类":"其他","系统类型":"压力废水管","系统名称":"YF 3","系统缩写":"YF","损失方法":"3bf616f9-6b98-4a21-80ff-da1120c8f6d6","管件材质":"钢塑复合","使用注释比例":"是","公称半径":"40 mm","公称直径":"80 mm","角度":"90.00°","尺寸":"80 mm-80 mm","图像":"<无>","设计选项":"主模型","IsCustom":"否","中心到端点":"78 mm","扎带外径":"97 mm","扎带宽度":"9 mm","管件外径":"89 mm","螺纹长度":"28 mm","金属厚度":"4 mm","长度 2":"78 mm","长度 1":"78 mm","管件外半径":"44 mm","找不到中心到端点":"80 mm","中心到端点标签":"78 mm","中心半径":"50 mm","扎带外半径":"48 mm","角度 1":"90.00°","K 系数":"0","构件分类编码":"20.80.05.20.04.05","类型图像":"<无>","成本":"0.00","查找表名称":"弯头 - 钢塑复合管 - 丝扣"}},{"uuid":"0a0035d8-93df-4331-9bc8-d4215dd0740c-001c6587","name":"","familyName":"管道-弯头-丝扣","typeName":"","typeId":-1,"revitId":"1860999","type":"Element","category":"OST_PipeFittingCenterLine","properties":{"Category":"中心线","Name":"","金属厚度":"4 mm","给排水工作压力":"0.0 Pa","管件材质":"钢塑复合","长度 2":"78 mm","长度 1":"78 mm","管件外半径":"44 mm","管件外径":"89 mm","公称半径":"40 mm","公称直径":"80 mm","找不到中心到端点":"80 mm","中心到端点":"78 mm","中心到端点标签":"78 mm","中心半径":"50 mm","螺纹长度":"28 mm","扎带外半径":"48 mm","扎带宽度":"9 mm","扎带外径":"97 mm","角度 1":"90.00°","角度":"90.00°","标高":"站厅层装修完成面","主体":"标高 : 站厅层装修完成面","偏移":"3500","系统分类":"其他","系统类型":"压力废水管","系统名称":"YF 3","系统缩写":"YF","损失方法":"3bf616f9-6b98-4a21-80ff-da1120c8f6d6","重要路径":"否","图像":"<无>","总体大小":"80 mm-80 mm","隔热层厚度":"0 mm","压降":"0.0 Pa","使用注释比例":"是","尺寸":"80 mm-80 mm","IsCustom":"否","创建的阶段":"新构造","拆除的阶段":"无","设计选项":"主模型"}},{"uuid":"0a0035d8-93df-4331-9bc8-d4215dd0740c-001c6598","name":"水管-内外热镀锌钢管","familyName":"管道类型","typeName":"水管-内外热镀锌钢管","typeId":1121512,"revitId":"1861016","type":"Pipe","category":"OST_PipeCurves","properties":{"Category":"管道","Name":"水管-内外热镀锌钢管","系统分类":"其他","系统类型":"压力废水管","系统名称":"YF 4","系统缩写":"YF","管段":"内外热镀锌钢管 - GB/T3091","直径":"80 mm","连接类型":"常规","粗糙度":"0.00200 mm","材质":"内外热镀锌钢管","规格/类型":"GB/T3091","管内底标高":"1040","剖面":"1","面积":"1","相对粗糙度":"0.000025","图像":"<无>","总体大小":"80 mm","隔热层厚度":"0 mm","外径":"89 mm","内径":"81 mm","尺寸":"80 mm","给排水工作压力":"0.0 Pa","管道材质":"<按类别>","气管管径":"0 mm","液管管径":"0 mm","创建的阶段":"新构造","拆除的阶段":"无","设计选项":"主模型","水平对正":"中心","垂直对正":"中","参照标高":"站厅层装修完成面","偏移":"3500","开始偏移":"3500","端点偏移":"3500","长度":"2126","坡度":"0.00%","类型图像":"<无>","成本":"0.00"}},{"uuid":"0a0035d8-93df-4331-9bc8-d4215dd0740c-001c6599","name":"","familyName":"管道类型","typeName":"","typeId":-1,"revitId":"1861017","type":"Element","category":"OST_PipeCurvesCenterLine","properties":{"Category":"中心线","Name":"","系统分类":"其他","系统类型":"压力废水管","系统名称":"YF 4","系统缩写":"YF","管段":"内外热镀锌钢管 - GB/T3091","直径":"80 mm","连接类型":"常规","粗糙度":"0.00200 mm","材质":"内外热镀锌钢管","规格/类型":"GB/T3091","管内底标高":"1040","剖面":"0","面积":"1","相对粗糙度":"0","图像":"<无>","总体大小":"80 mm","隔热层厚度":"0 mm","外径":"89 mm","内径":"81 mm","尺寸":"80 mm","给排水工作压力":"0.0 Pa","管道材质":"<按类别>","气管管径":"0 mm","液管管径":"0 mm","创建的阶段":"新构造","拆除的阶段":"无","设计选项":"主模型","水平对正":"中心","垂直对正":"中","参照标高":"站厅层装修完成面","偏移":"3500","开始偏移":"3500","端点偏移":"3500","长度":"2126","坡度":"0.00%"}},{"uuid":"0a0035d8-93df-4331-9bc8-d4215dd0740c-001c659a","name":"YF 4","familyName":"管道系统","typeName":"YF 4","typeId":976772,"revitId":"1861018","type":"PipingSystem","category":"OST_PipingSystem","properties":{"Category":"管道系统","Name":"YF 4","图像":"<无>","图元数":"0","系统名称":"YF 4","体积":"17.5 L","设计选项":"主模型","类型图像":"<无>","双线下降符号":"阴阳","双线上升符号":"轮廓","单线下降符号":"弯曲 - ¾ 圆","单线上升符号":"轮廓","单线 T 形三通向上符号":"轮廓","单线 T 形三通向下符号":"T 形三通 - 半圆","计算":"无","缩写":"YF","系统分类":"其他","材质":"MEP_压力废水管系统颜色"}},{"uuid":"0a0035d8-93df-4331-9bc8-d4215dd0740c-001c65a0","name":"水管-内外热镀锌钢管","familyName":"管道类型","typeName":"水管-内外热镀锌钢管","typeId":1121512,"revitId":"1861024","type":"Pipe","category":"OST_PipeCurves","properties":{"Category":"管道","Name":"水管-内外热镀锌钢管","系统分类":"其他","系统类型":"压力废水管","系统名称":"YF 4","系统缩写":"YF","管段":"内外热镀锌钢管 - GB/T3091","直径":"80 mm","连接类型":"常规","粗糙度":"0.00200 mm","材质":"内外热镀锌钢管","规格/类型":"GB/T3091","管内底标高":"1040","剖面":"1","面积":"0","相对粗糙度":"0.000025","图像":"<无>","总体大小":"80 mm","隔热层厚度":"0 mm","外径":"89 mm","内径":"81 mm","尺寸":"80 mm","给排水工作压力":"0.0 Pa","管道材质":"<按类别>","气管管径":"0 mm","液管管径":"0 mm","创建的阶段":"新构造","拆除的阶段":"无","设计选项":"主模型","水平对正":"中心","垂直对正":"中","参照标高":"站厅层装修完成面","偏移":"3500","开始偏移":"3500","端点偏移":"3500","长度":"1122","坡度":"0.00%","类型图像":"<无>","成本":"0.00"}},{"uuid":"0a0035d8-93df-4331-9bc8-d4215dd0740c-001c65a1","name":"","familyName":"管道类型","typeName":"","typeId":-1,"revitId":"1861025","type":"Element","category":"OST_PipeCurvesCenterLine","properties":{"Category":"中心线","Name":"","系统分类":"其他","系统类型":"压力废水管","系统名称":"YF 4","系统缩写":"YF","管段":"内外热镀锌钢管 - GB/T3091","直径":"80 mm","连接类型":"常规","粗糙度":"0.00200 mm","材质":"内外热镀锌钢管","规格/类型":"GB/T3091","管内底标高":"1040","剖面":"0","面积":"0","相对粗糙度":"0","图像":"<无>","总体大小":"80 mm","隔热层厚度":"0 mm","外径":"89 mm","内径":"81 mm","尺寸":"80 mm","给排水工作压力":"0.0 Pa","管道材质":"<按类别>","气管管径":"0 mm","液管管径":"0 mm","创建的阶段":"新构造","拆除的阶段":"无","设计选项":"主模型","水平对正":"中心","垂直对正":"中","参照标高":"站厅层装修完成面","偏移":"3500","开始偏移":"3500","端点偏移":"3500","长度":"1122","坡度":"0.00%"}},{"uuid":"0a0035d8-93df-4331-9bc8-d4215dd0740c-001c65a6","name":"弯头-丝扣","familyName":"管道-弯头-丝扣","typeName":"弯头-丝扣","typeId":1088740,"revitId":"1861030","type":"FamilyInstance","category":"OST_PipeFitting","properties":{"Category":"管件","Name":"弯头-丝扣","总体大小":"80 mm-80 mm","隔热层厚度":"0 mm","重要路径":"否","压降":"0.0 Pa","标高":"站厅层装修完成面","主体":"标高 : 站厅层装修完成面","偏移":"3500","创建的阶段":"新构造","拆除的阶段":"无","给排水工作压力":"0.0 Pa","系统分类":"其他","系统类型":"压力废水管","系统名称":"YF 4","系统缩写":"YF","损失方法":"3bf616f9-6b98-4a21-80ff-da1120c8f6d6","管件材质":"钢塑复合","使用注释比例":"是","公称半径":"40 mm","公称直径":"80 mm","角度":"90.00°","尺寸":"80 mm-80 mm","图像":"<无>","设计选项":"主模型","IsCustom":"否","中心到端点":"78 mm","扎带外径":"97 mm","扎带宽度":"9 mm","管件外径":"89 mm","螺纹长度":"28 mm","金属厚度":"4 mm","长度 2":"78 mm","长度 1":"78 mm","管件外半径":"44 mm","找不到中心到端点":"80 mm","中心到端点标签":"78 mm","中心半径":"50 mm","扎带外半径":"48 mm","角度 1":"90.00°","K 系数":"0","构件分类编码":"20.80.05.20.04.05","类型图像":"<无>","成本":"0.00","查找表名称":"弯头 - 钢塑复合管 - 丝扣"}},{"uuid":"0a0035d8-93df-4331-9bc8-d4215dd0740c-001c65a7","name":"","familyName":"管道-弯头-丝扣","typeName":"","typeId":-1,"revitId":"1861031","type":"Element","category":"OST_PipeFittingCenterLine","properties":{"Category":"中心线","Name":"","金属厚度":"4 mm","给排水工作压力":"0.0 Pa","管件材质":"钢塑复合","长度 2":"78 mm","长度 1":"78 mm","管件外半径":"44 mm","管件外径":"89 mm","公称半径":"40 mm","公称直径":"80 mm","找不到中心到端点":"80 mm","中心到端点":"78 mm","中心到端点标签":"78 mm","中心半径":"50 mm","螺纹长度":"28 mm","扎带外半径":"48 mm","扎带宽度":"9 mm","扎带外径":"97 mm","角度 1":"90.00°","角度":"90.00°","标高":"站厅层装修完成面","主体":"标高 : 站厅层装修完成面","偏移":"3500","系统分类":"其他","系统类型":"压力废水管","系统名称":"YF 4","系统缩写":"YF","损失方法":"3bf616f9-6b98-4a21-80ff-da1120c8f6d6","重要路径":"否","图像":"<无>","总体大小":"80 mm-80 mm","隔热层厚度":"0 mm","压降":"0.0 Pa","使用注释比例":"是","尺寸":"80 mm-80 mm","IsCustom":"否","创建的阶段":"新构造","拆除的阶段":"无","设计选项":"主模型"}},{"uuid":"0a0035d8-93df-4331-9bc8-d4215dd0740c-001c65b4","name":"YF 5","familyName":"管道系统","typeName":"YF 5","typeId":976772,"revitId":"1861044","type":"PipingSystem","category":"OST_PipingSystem","properties":{"Category":"管道系统","Name":"YF 5","图像":"<无>","图元数":"0","系统名称":"YF 5","体积":"59.1 L","设计选项":"主模型","类型图像":"<无>","双线下降符号":"阴阳","双线上升符号":"轮廓","单线下降符号":"弯曲 - ¾ 圆","单线上升符号":"轮廓","单线 T 形三通向上符号":"轮廓","单线 T 形三通向下符号":"T 形三通 - 半圆","计算":"无","缩写":"YF","系统分类":"其他","材质":"MEP_压力废水管系统颜色"}},{"uuid":"0a0035d8-93df-4331-9bc8-d4215dd0740c-001c65ba","name":"水管-内外热镀锌钢管","familyName":"管道类型","typeName":"水管-内外热镀锌钢管","typeId":1121512,"revitId":"1861050","type":"Pipe","category":"OST_PipeCurves","properties":{"Category":"管道","Name":"水管-内外热镀锌钢管","系统分类":"其他","系统类型":"压力废水管","系统名称":"YF 5","系统缩写":"YF","管段":"内外热镀锌钢管 - GB/T3091","直径":"80 mm","连接类型":"常规","粗糙度":"0.00200 mm","材质":"内外热镀锌钢管","规格/类型":"GB/T3091","管内底标高":"1040","剖面":"2","面积":"1","相对粗糙度":"0.000025","图像":"<无>","总体大小":"80 mm","隔热层厚度":"0 mm","外径":"89 mm","内径":"81 mm","尺寸":"80 mm","给排水工作压力":"0.0 Pa","管道材质":"<按类别>","气管管径":"0 mm","液管管径":"0 mm","创建的阶段":"新构造","拆除的阶段":"无","设计选项":"主模型","水平对正":"中心","垂直对正":"中","参照标高":"站厅层装修完成面","偏移":"3500","开始偏移":"3500","端点偏移":"3500","长度":"2425","坡度":"0.00%","类型图像":"<无>","成本":"0.00"}},{"uuid":"0a0035d8-93df-4331-9bc8-d4215dd0740c-001c65bb","name":"","familyName":"管道类型","typeName":"","typeId":-1,"revitId":"1861051","type":"Element","category":"OST_PipeCurvesCenterLine","properties":{"Category":"中心线","Name":"","系统分类":"其他","系统类型":"压力废水管","系统名称":"YF 5","系统缩写":"YF","管段":"内外热镀锌钢管 - GB/T3091","直径":"80 mm","连接类型":"常规","粗糙度":"0.00200 mm","材质":"内外热镀锌钢管","规格/类型":"GB/T3091","管内底标高":"1040","剖面":"0","面积":"1","相对粗糙度":"0","图像":"<无>","总体大小":"80 mm","隔热层厚度":"0 mm","外径":"89 mm","内径":"81 mm","尺寸":"80 mm","给排水工作压力":"0.0 Pa","管道材质":"<按类别>","气管管径":"0 mm","液管管径":"0 mm","创建的阶段":"新构造","拆除的阶段":"无","设计选项":"主模型","水平对正":"中心","垂直对正":"中","参照标高":"站厅层装修完成面","偏移":"3500","开始偏移":"3500","端点偏移":"3500","长度":"2425","坡度":"0.00%"}},{"uuid":"0a0035d8-93df-4331-9bc8-d4215dd0740c-001c65c0","name":"水管-内外热镀锌钢管","familyName":"管道类型","typeName":"水管-内外热镀锌钢管","typeId":1121512,"revitId":"1861056","type":"Pipe","category":"OST_PipeCurves","properties":{"Category":"管道","Name":"水管-内外热镀锌钢管","系统分类":"其他","系统类型":"压力废水管","系统名称":"YF 5","系统缩写":"YF","管段":"内外热镀锌钢管 - GB/T3091","直径":"80 mm","连接类型":"常规","粗糙度":"0.00200 mm","材质":"内外热镀锌钢管","规格/类型":"GB/T3091","管内底标高":"1040","剖面":"2","面积":"1","相对粗糙度":"0.000025","图像":"<无>","总体大小":"80 mm","隔热层厚度":"0 mm","外径":"89 mm","内径":"81 mm","尺寸":"80 mm","给排水工作压力":"0.0 Pa","管道材质":"<按类别>","气管管径":"0 mm","液管管径":"0 mm","创建的阶段":"新构造","拆除的阶段":"无","设计选项":"主模型","水平对正":"中心","垂直对正":"中","参照标高":"站厅层装修完成面","偏移":"3500","开始偏移":"3500","端点偏移":"3500","长度":"4947","坡度":"0.00%","类型图像":"<无>","成本":"0.00"}},{"uuid":"0a0035d8-93df-4331-9bc8-d4215dd0740c-001c65c1","name":"","familyName":"管道类型","typeName":"","typeId":-1,"revitId":"1861057","type":"Element","category":"OST_PipeCurvesCenterLine","properties":{"Category":"中心线","Name":"","系统分类":"其他","系统类型":"压力废水管","系统名称":"YF 5","系统缩写":"YF","管段":"内外热镀锌钢管 - GB/T3091","直径":"80 mm","连接类型":"常规","粗糙度":"0.00200 mm","材质":"内外热镀锌钢管","规格/类型":"GB/T3091","管内底标高":"1040","剖面":"0","面积":"1","相对粗糙度":"0","图像":"<无>","总体大小":"80 mm","隔热层厚度":"0 mm","外径":"89 mm","内径":"81 mm","尺寸":"80 mm","给排水工作压力":"0.0 Pa","管道材质":"<按类别>","气管管径":"0 mm","液管管径":"0 mm","创建的阶段":"新构造","拆除的阶段":"无","设计选项":"主模型","水平对正":"中心","垂直对正":"中","参照标高":"站厅层装修完成面","偏移":"3500","开始偏移":"3500","端点偏移":"3500","长度":"4947","坡度":"0.00%"}},{"uuid":"0a0035d8-93df-4331-9bc8-d4215dd0740c-001c65c6","name":"弯头-丝扣","familyName":"管道-弯头-丝扣","typeName":"弯头-丝扣","typeId":1088740,"revitId":"1861062","type":"FamilyInstance","category":"OST_PipeFitting","properties":{"Category":"管件","Name":"弯头-丝扣","总体大小":"80 mm-80 mm","隔热层厚度":"0 mm","重要路径":"否","压降":"0.0 Pa","标高":"站厅层装修完成面","主体":"标高 : 站厅层装修完成面","偏移":"3500","创建的阶段":"新构造","拆除的阶段":"无","给排水工作压力":"0.0 Pa","系统分类":"其他","系统类型":"压力废水管","系统名称":"YF 5","系统缩写":"YF","损失方法":"3bf616f9-6b98-4a21-80ff-da1120c8f6d6","管件材质":"钢塑复合","使用注释比例":"是","公称半径":"40 mm","公称直径":"80 mm","角度":"90.00°","尺寸":"80 mm-80 mm","图像":"<无>","设计选项":"主模型","IsCustom":"否","中心到端点":"78 mm","扎带外径":"97 mm","扎带宽度":"9 mm","管件外径":"89 mm","螺纹长度":"28 mm","金属厚度":"4 mm","长度 2":"78 mm","长度 1":"78 mm","管件外半径":"44 mm","找不到中心到端点":"80 mm","中心到端点标签":"78 mm","中心半径":"50 mm","扎带外半径":"48 mm","角度 1":"90.00°","K 系数":"0","构件分类编码":"20.80.05.20.04.05","类型图像":"<无>","成本":"0.00","查找表名称":"弯头 - 钢塑复合管 - 丝扣"}},{"uuid":"0a0035d8-93df-4331-9bc8-d4215dd0740c-001c65c7","name":"","familyName":"管道-弯头-丝扣","typeName":"","typeId":-1,"revitId":"1861063","type":"Element","category":"OST_PipeFittingCenterLine","properties":{"Category":"中心线","Name":"","金属厚度":"4 mm","给排水工作压力":"0.0 Pa","管件材质":"钢塑复合","长度 2":"78 mm","长度 1":"78 mm","管件外半径":"44 mm","管件外径":"89 mm","公称半径":"40 mm","公称直径":"80 mm","找不到中心到端点":"80 mm","中心到端点":"78 mm","中心到端点标签":"78 mm","中心半径":"50 mm","螺纹长度":"28 mm","扎带外半径":"48 mm","扎带宽度":"9 mm","扎带外径":"97 mm","角度 1":"90.00°","角度":"90.00°","标高":"站厅层装修完成面","主体":"标高 : 站厅层装修完成面","偏移":"3500","系统分类":"其他","系统类型":"压力废水管","系统名称":"YF 5","系统缩写":"YF","损失方法":"3bf616f9-6b98-4a21-80ff-da1120c8f6d6","重要路径":"否","图像":"<无>","总体大小":"80 mm-80 mm","隔热层厚度":"0 mm","压降":"0.0 Pa","使用注释比例":"是","尺寸":"80 mm-80 mm","IsCustom":"否","创建的阶段":"新构造","拆除的阶段":"无","设计选项":"主模型"}},{"uuid":"0a0035d8-93df-4331-9bc8-d4215dd0740c-001c65c8","name":"水管-内外热镀锌钢管","familyName":"管道类型","typeName":"水管-内外热镀锌钢管","typeId":1121512,"revitId":"1861064","type":"Pipe","category":"OST_PipeCurves","properties":{"Category":"管道","Name":"水管-内外热镀锌钢管","系统分类":"其他","系统类型":"压力废水管","系统名称":"YF 5","系统缩写":"YF","管段":"内外热镀锌钢管 - GB/T3091","直径":"80 mm","连接类型":"常规","粗糙度":"0.00200 mm","材质":"内外热镀锌钢管","规格/类型":"GB/T3091","管内底标高":"1040","剖面":"2","面积":"1","相对粗糙度":"0.000025","图像":"<无>","总体大小":"80 mm","隔热层厚度":"0 mm","外径":"89 mm","内径":"81 mm","尺寸":"80 mm","给排水工作压力":"0.0 Pa","管道材质":"<按类别>","气管管径":"0 mm","液管管径":"0 mm","创建的阶段":"新构造","拆除的阶段":"无","设计选项":"主模型","水平对正":"中心","垂直对正":"中","参照标高":"站厅层装修完成面","偏移":"3500","开始偏移":"3500","端点偏移":"3500","长度":"3707","坡度":"0.00%","类型图像":"<无>","成本":"0.00"}},{"uuid":"0a0035d8-93df-4331-9bc8-d4215dd0740c-001c65c9","name":"","familyName":"管道类型","typeName":"","typeId":-1,"revitId":"1861065","type":"Element","category":"OST_PipeCurvesCenterLine","properties":{"Category":"中心线","Name":"","系统分类":"其他","系统类型":"压力废水管","系统名称":"YF 5","系统缩写":"YF","管段":"内外热镀锌钢管 - GB/T3091","直径":"80 mm","连接类型":"常规","粗糙度":"0.00200 mm","材质":"内外热镀锌钢管","规格/类型":"GB/T3091","管内底标高":"1040","剖面":"0","面积":"1","相对粗糙度":"0","图像":"<无>","总体大小":"80 mm","隔热层厚度":"0 mm","外径":"89 mm","内径":"81 mm","尺寸":"80 mm","给排水工作压力":"0.0 Pa","管道材质":"<按类别>","气管管径":"0 mm","液管管径":"0 mm","创建的阶段":"新构造","拆除的阶段":"无","设计选项":"主模型","水平对正":"中心","垂直对正":"中","参照标高":"站厅层装修完成面","偏移":"3500","开始偏移":"3500","端点偏移":"3500","长度":"3707","坡度":"0.00%"}},{"uuid":"0a0035d8-93df-4331-9bc8-d4215dd0740c-001c65d0","name":"弯头-丝扣","familyName":"管道-弯头-丝扣","typeName":"弯头-丝扣","typeId":1088740,"revitId":"1861072","type":"FamilyInstance","category":"OST_PipeFitting","properties":{"Category":"管件","Name":"弯头-丝扣","总体大小":"80 mm-80 mm","隔热层厚度":"0 mm","重要路径":"否","压降":"0.0 Pa","标高":"站厅层装修完成面","主体":"标高 : 站厅层装修完成面","偏移":"3500","创建的阶段":"新构造","拆除的阶段":"无","给排水工作压力":"0.0 Pa","系统分类":"其他","系统类型":"压力废水管","系统名称":"YF 5","系统缩写":"YF","损失方法":"3bf616f9-6b98-4a21-80ff-da1120c8f6d6","管件材质":"钢塑复合","使用注释比例":"是","公称半径":"40 mm","公称直径":"80 mm","角度":"90.00°","尺寸":"80 mm-80 mm","图像":"<无>","设计选项":"主模型","IsCustom":"否","中心到端点":"78 mm","扎带外径":"97 mm","扎带宽度":"9 mm","管件外径":"89 mm","螺纹长度":"28 mm","金属厚度":"4 mm","长度 2":"78 mm","长度 1":"78 mm","管件外半径":"44 mm","找不到中心到端点":"80 mm","中心到端点标签":"78 mm","中心半径":"50 mm","扎带外半径":"48 mm","角度 1":"90.00°","K 系数":"0","构件分类编码":"20.80.05.20.04.05","类型图像":"<无>","成本":"0.00","查找表名称":"弯头 - 钢塑复合管 - 丝扣"}},{"uuid":"0a0035d8-93df-4331-9bc8-d4215dd0740c-001c65d1","name":"","familyName":"管道-弯头-丝扣","typeName":"","typeId":-1,"revitId":"1861073","type":"Element","category":"OST_PipeFittingCenterLine","properties":{"Category":"中心线","Name":"","金属厚度":"4 mm","给排水工作压力":"0.0 Pa","管件材质":"钢塑复合","长度 2":"78 mm","长度 1":"78 mm","管件外半径":"44 mm","管件外径":"89 mm","公称半径":"40 mm","公称直径":"80 mm","找不到中心到端点":"80 mm","中心到端点":"78 mm","中心到端点标签":"78 mm","中心半径":"50 mm","螺纹长度":"28 mm","扎带外半径":"48 mm","扎带宽度":"9 mm","扎带外径":"97 mm","角度 1":"90.00°","角度":"90.00°","标高":"站厅层装修完成面","主体":"标高 : 站厅层装修完成面","偏移":"3500","系统分类":"其他","系统类型":"压力废水管","系统名称":"YF 5","系统缩写":"YF","损失方法":"3bf616f9-6b98-4a21-80ff-da1120c8f6d6","重要路径":"否","图像":"<无>","总体大小":"80 mm-80 mm","隔热层厚度":"0 mm","压降":"0.0 Pa","使用注释比例":"是","尺寸":"80 mm-80 mm","IsCustom":"否","创建的阶段":"新构造","拆除的阶段":"无","设计选项":"主模型"}},{"uuid":"0a0035d8-93df-4331-9bc8-d4215dd0740c-001c65da","name":"弯头-丝扣","familyName":"管道-弯头-丝扣","typeName":"弯头-丝扣","typeId":1088740,"revitId":"1861082","type":"FamilyInstance","category":"OST_PipeFitting","properties":{"Category":"管件","Name":"弯头-丝扣","总体大小":"80 mm-80 mm","隔热层厚度":"0 mm","重要路径":"否","压降":"0.0 Pa","标高":"站厅层装修完成面","主体":"标高 : 站厅层装修完成面","偏移":"3500","创建的阶段":"新构造","拆除的阶段":"无","给排水工作压力":"0.0 Pa","系统分类":"其他","系统类型":"压力废水管","系统名称":"YF 5","系统缩写":"YF","损失方法":"3bf616f9-6b98-4a21-80ff-da1120c8f6d6","管件材质":"钢塑复合","使用注释比例":"是","公称半径":"40 mm","公称直径":"80 mm","角度":"45.00°","尺寸":"80 mm-80 mm","图像":"<无>","设计选项":"主模型","IsCustom":"否","中心到端点":"54 mm","扎带外径":"97 mm","扎带宽度":"9 mm","管件外径":"89 mm","螺纹长度":"28 mm","金属厚度":"4 mm","长度 2":"38 mm","长度 1":"92 mm","管件外半径":"44 mm","找不到中心到端点":"54 mm","中心到端点标签":"54 mm","中心半径":"63 mm","扎带外半径":"48 mm","角度 1":"45.00°","K 系数":"0","构件分类编码":"20.80.05.20.04.05","类型图像":"<无>","成本":"0.00","查找表名称":"弯头 - 钢塑复合管 - 丝扣"}},{"uuid":"0a0035d8-93df-4331-9bc8-d4215dd0740c-001c65db","name":"","familyName":"管道-弯头-丝扣","typeName":"","typeId":-1,"revitId":"1861083","type":"Element","category":"OST_PipeFittingCenterLine","properties":{"Category":"中心线","Name":"","金属厚度":"4 mm","给排水工作压力":"0.0 Pa","管件材质":"钢塑复合","长度 2":"38 mm","长度 1":"92 mm","管件外半径":"44 mm","管件外径":"89 mm","公称半径":"40 mm","公称直径":"80 mm","找不到中心到端点":"54 mm","中心到端点":"54 mm","中心到端点标签":"54 mm","中心半径":"63 mm","螺纹长度":"28 mm","扎带外半径":"48 mm","扎带宽度":"9 mm","扎带外径":"97 mm","角度 1":"45.00°","角度":"45.00°","标高":"站厅层装修完成面","主体":"标高 : 站厅层装修完成面","偏移":"3500","系统分类":"其他","系统类型":"压力废水管","系统名称":"YF 5","系统缩写":"YF","损失方法":"3bf616f9-6b98-4a21-80ff-da1120c8f6d6","重要路径":"否","图像":"<无>","总体大小":"80 mm-80 mm","隔热层厚度":"0 mm","压降":"0.0 Pa","使用注释比例":"是","尺寸":"80 mm-80 mm","IsCustom":"否","创建的阶段":"新构造","拆除的阶段":"无","设计选项":"主模型"}},{"uuid":"b42c4229-ef3c-4276-b6d4-7665165729ff-001c7b21","name":"XH 2","familyName":"管道系统","typeName":"XH 2","typeId":976768,"revitId":"1866529","type":"PipingSystem","category":"OST_PipingSystem","properties":{"Category":"管道系统","Name":"XH 2","图像":"<无>","图元数":"0","系统名称":"XH 2","体积":"34.1 L","设计选项":"主模型","类型图像":"<无>","双线下降符号":"阴阳","双线上升符号":"轮廓","单线下降符号":"弯曲 - ¾ 圆","单线上升符号":"轮廓","单线 T 形三通向上符号":"轮廓","单线 T 形三通向下符号":"T 形三通 - 半圆","计算":"无","缩写":"XH","系统分类":"湿式消防系统","材质":"MEP_消防水管系统颜色"}},{"uuid":"d27e2c1e-7306-446b-aeee-e5d50412a02e-0021850e","name":"J 4","familyName":"管道系统","typeName":"J 4","typeId":976767,"revitId":"2196750","type":"PipingSystem","category":"OST_PipingSystem","properties":{"Category":"管道系统","Name":"J 4","图像":"<无>","图元数":"0","系统名称":"J 4","体积":"11.5 L","静压":"0.0 Pa","流量":"0.0 L/s","设计选项":"主模型","卫浴装置当量":"0","类型图像":"<无>","双线下降符号":"阴阳","双线上升符号":"轮廓","单线下降符号":"弯曲 - ¾ 圆","单线上升符号":"轮廓","单线 T 形三通向上符号":"轮廓","单线 T 形三通向下符号":"T 形三通 - 半圆","计算":"全部","缩写":"J","系统分类":"家用冷水","流体类型":"水","流体温度":"16 °C","流体动态粘度":"0.00112 Pa-s","流体密度":"998.9114 kg/m³","材质":"MEP_给水管系统颜色","流量转换方法":"主冲洗阀"}}]}}